Metadata-Version: 2.1
Name: liveupstoxoc
Version: 0.1.4
Summary: To scrape live optionschain data from upstox for free (without api)
Home-page: https://github.com/MaticAlgos
Author: Niraj Munot
Author-email: nirajmunot28@gmail.com
License: MIT
Download-URL: https://github.com/MaticAlgos/liveupstoxoc/archive/refs/tags/0.1.3.tar.gz
Keywords: upstox,optionschain,liveoptionschain,NSE,openinterest
Platform: UNKNOWN
Classifier: Development Status :: 3 - Alpha
Classifier: Intended Audience :: Developers
Classifier: Topic :: Software Development :: Build Tools
Classifier: License :: OSI Approved :: MIT License
Classifier: Programming Language :: Python :: 3
Classifier: Programming Language :: Python :: 3.4
Classifier: Programming Language :: Python :: 3.5
Classifier: Programming Language :: Python :: 3.6
